flask_firebase/__init__.py
flask_firebase/templates/firebase_auth/widget.html
flask_firebase/templates/firebase_auth/widget_base.html
flask_firebase-1.7.dist-info/LICENSE
flask_firebase-1.7.dist-info/METADATA
flask_firebase-1.7.dist-info/WHEEL
flask_firebase-1.7.dist-info/top_level.txt
flask_firebase-1.7.dist-info/RECORD
