Metadata-Version: 2.1
Name: flask_firebase
Version: 1.7
Summary: Google Firebase integration for flask. Forked from klokantech/flask-firebase
Author-email: Mark Hughes <markh@markhughes.tech>
Project-URL: Homepage, https://github.com/markphughes17/flask-firebase
Project-URL: Issues, https://github.com/markphughes17/flask-firebase/issues
Classifier: Programming Language :: Python :: 3
Classifier: License :: OSI Approved :: MIT License
Classifier: Operating System :: OS Independent
Requires-Python: >=3.8
License-File: LICENSE
